st2auth_flat_file_backend/__init__.py
st2auth_flat_file_backend/apr1.py
st2auth_flat_file_backend/flat_file.py
tests/__init__.py
tests/unit/__init__.py
tests/unit/test_flat_file_backend.py
st2_auth_backend_flat_file-0.4.1.dist-info/LICENSE
st2_auth_backend_flat_file-0.4.1.dist-info/METADATA
st2_auth_backend_flat_file-0.4.1.dist-info/WHEEL
st2_auth_backend_flat_file-0.4.1.dist-info/entry_points.txt
st2_auth_backend_flat_file-0.4.1.dist-info/top_level.txt
st2_auth_backend_flat_file-0.4.1.dist-info/RECORD
